{"basename":"upload","fileperms":"0755","filetype":"dir","is_readable":true,"is_writeable":true,"is_link":false,"is_dir":true,"mime":"directory","mtime":1701680393,"path":"","url_path":"examples/upload","dirsize":7415187,"files_count":5,"images_count":5,"preview":"borki_mond.jpg","files":{"borki_mond.jpg":{"basename":"borki_mond.jpg","fileperms":"0644","filetype":"file","filesize":4622007,"is_readable":true,"is_writeable":true,"is_link":false,"is_dir":false,"mtime":1701668545,"path":"borki_mond.jpg","ext":"jpg","url_path":"examples/upload/borki_mond.jpg","icon":"image","mime":"image/jpeg","image":{"width":2116,"height":2832,"type":2,"bits":8,"channels":3,"mime":"image/jpeg"}},"Martin_fight.jpg":{"basename":"Martin_fight.jpg","fileperms":"0644","filetype":"file","filesize":637052,"is_readable":true,"is_writeable":true,"is_link":false,"is_dir":false,"mtime":1701680393,"path":"Martin_fight.jpg","ext":"jpg","url_path":"examples/upload/Martin_fight.jpg","icon":"image","mime":"image/jpeg","image":{"width":812,"height":583,"type":2,"bits":8,"channels":3,"mime":"image/jpeg"}},"test.png":{"basename":"test.png","fileperms":"0644","filetype":"file","filesize":1012241,"is_readable":true,"is_writeable":true,"is_link":false,"is_dir":false,"mtime":1701680340,"path":"test.png","ext":"png","url_path":"examples/upload/test.png","icon":"image","mime":"image/png","image":{"width":1034,"height":1044,"type":3,"bits":8,"mime":"image/png"}},"test2.jpg":{"basename":"test2.jpg","fileperms":"0644","filetype":"file","filesize":424438,"is_readable":true,"is_writeable":true,"is_link":false,"is_dir":false,"mtime":1701680349,"path":"test2.jpg","ext":"jpg","url_path":"examples/upload/test2.jpg","icon":"image","mime":"image/jpeg","image":{"width":1500,"height":739,"type":2,"bits":8,"channels":3,"mime":"image/jpeg"}},"test test.png":{"basename":"test test.png","fileperms":"0644","filetype":"file","filesize":719449,"is_readable":true,"is_writeable":true,"is_link":false,"is_dir":false,"mtime":1701680319,"path":"test test.png","ext":"png","url_path":"examples/upload/test test.png","icon":"image","mime":"image/png","image":{"width":1024,"height":1024,"type":3,"bits":8,"mime":"image/png"}}}}